pipe_io_server/__init__.py
pipe_io_server/deque.py
pipe_io_server/pipe.py
pipe_io_server/pipe_io_server.py
pipe_io_server/pipe_io_thread.py
pipe_io_server/pipe_reader_server.py
pipe_io_server/pipe_reader_thread.py
pipe_io_server/pipe_writer_server.py
pipe_io_server/pipe_writer_thread.py
pipe_io_server/terminate_process_on_failure.py
pipe_io_server/test_pipe_io_server.py
pipe_io_server/clients/c_cpp/example.c
pipe_io_server/clients/c_cpp/example.cpp
pipe_io_server/clients/c_cpp/pipe_io.h
pipe_io_server/clients/c_cpp/pipe_io.hpp
pipe_io_server/clients/csharp/Example.cs
pipe_io_server/clients/csharp/PipeIO.cs
pipe_io_server/clients/go/example.go
pipe_io_server/clients/java/Example.java
pipe_io_server/clients/java/MessageHandler.java
pipe_io_server/clients/java/PipeIO.java
pipe_io_server/clients/java/PipeReader.java
pipe_io_server/clients/java/PipeWriter.java
pipe_io_server/clients/python/example.py
pipe_io_server/clients/python/pipe_io.py
pipe_io_server-1.0.3.dist-info/LICENSE
pipe_io_server-1.0.3.dist-info/METADATA
pipe_io_server-1.0.3.dist-info/WHEEL
pipe_io_server-1.0.3.dist-info/top_level.txt
pipe_io_server-1.0.3.dist-info/RECORD
