Metadata-Version: 2.1
Name: pipe-io-server
Version: 1.0.3
Summary: A trivial to use IPC solution based on pipes and newlines
Home-page: https://git.strongds.hu/mrtoth/pipe-io-server
Author: Kristóf Tóth
Author-email: mrtoth@strongds.hu
License: UNKNOWN
Platform: UNKNOWN
Classifier: Programming Language :: Python :: 3
Classifier: License :: OSI Approved :: MIT License
Classifier: Operating System :: POSIX
